klio_devtools/__init__.py
klio_devtools/cli.py
klio_devtools/commands/develop.py
klio_devtools-0.1.1.dist-info/METADATA
klio_devtools-0.1.1.dist-info/WHEEL
klio_devtools-0.1.1.dist-info/entry_points.txt
klio_devtools-0.1.1.dist-info/top_level.txt
klio_devtools-0.1.1.dist-info/RECORD
