Metadata-Version: 2.1
Name: klio-devtools
Version: 0.1.1
Summary: Utilities to make klio development a little easier.
Home-page: https://github.com/spotify/klio
Author: The klio developers
Author-email: opensource+klio@spotify.com
Maintainer: The klio developers
Maintainer-email: opensource+klio@spotify.com
License: UNKNOWN
Project-URL: Documentation, https://docs.klio.io
Project-URL: Bug Tracker, https://github.com/spotify/klio/issues
Project-URL: Source Code, https://github.com/spotify/klio
Keywords: klio,apache,beam,audio
Platform: UNKNOWN
Classifier: Development Status :: 3 - Alpha
Classifier: Natural Language :: English
Classifier: Operating System :: POSIX :: Linux
Classifier: Operating System :: MacOS :: MacOS X
Classifier: Programming Language :: Python
Classifier: Programming Language :: Python :: 3.6
Classifier: Programming Language :: Python :: 3.7
Classifier: Programming Language :: Python :: 3.8
Classifier: Programming Language :: Python :: Implementation :: CPython
Classifier: License :: OSI Approved :: Apache Software License
Classifier: Topic :: Software Development :: Libraries
Classifier: Topic :: Software Development :: Libraries :: Python Modules
Classifier: Topic :: Multimedia
Classifier: Topic :: Multimedia :: Graphics
Classifier: Topic :: Multimedia :: Sound/Audio
Classifier: Topic :: Multimedia :: Video
Classifier: Topic :: Scientific/Engineering
Classifier: Topic :: Scientific/Engineering :: Image Processing
Requires-Python: >=3.6, <3.9
Requires-Dist: click
Requires-Dist: docker
Requires-Dist: dockerpty
Requires-Dist: klio-cli (>=1.0.0)
Requires-Dist: klio-core (>=0.2.0)
Provides-Extra: dev
Requires-Dist: coverage ; extra == 'dev'
Requires-Dist: pytest ; extra == 'dev'
Requires-Dist: pytest-cov ; extra == 'dev'
Requires-Dist: pytest-mock ; extra == 'dev'
Requires-Dist: bumpversion ; extra == 'dev'
Requires-Dist: wheel ; extra == 'dev'
Provides-Extra: tests
Requires-Dist: coverage ; extra == 'tests'
Requires-Dist: pytest ; extra == 'tests'
Requires-Dist: pytest-cov ; extra == 'tests'
Requires-Dist: pytest-mock ; extra == 'tests'
